<?xml version="1.0"?>
<ItemConsumable name="Slimfast" weight="0.5" value="250">
	<description>A knock-off of the brand of weight-loss
		pill that destroyed diet culture.</description>
	<effectmutator>
		<criteriaValue part="breasts" variable="size" value="1" />
		<mutation part="breasts" variable="size" modifier="-1">
		</mutation>
	</effectmutator>
	<effectmutator>
		<criteriaValue part="butt" variable="size" value="1" />
		<mutation part="butt" variable="size" modifier="-1">
		</mutation>
	</effectmutator>
	<effectmutator>
		<criteriaValue part="body" variable="weight" value="25" />
		<mutation part="body" variable="weight" modifier="-25">
			You take the
			slimfast, and wow, they weren't kidding about the fast part.
			You drop to a
			MACRObody_weight_desc build, your bust has become a
			MACRObreast_size_desc pair, while a slimmer, MACRObutt_size_desc
			ass now sits on your slenderer thighs. 
		</mutation>
	</effectmutator>

</ItemConsumable>